awesome_list/__init__.py
awesome_list/__main__.py
awesome_list/awesome_items.py
awesome_list/cli.py
awesome_list/default_config.py
awesome_list/generator.py
awesome_list/logger.py
awesome_list/markdown_writer.py
awesome_list/py.typed
awesome_list/utils.py
awesome_lists_generator-0.2.2.dist-info/licenses/LICENSE
awesome_lists_generator-0.2.2.dist-info/METADATA
awesome_lists_generator-0.2.2.dist-info/WHEEL
awesome_lists_generator-0.2.2.dist-info/entry_points.txt
awesome_lists_generator-0.2.2.dist-info/top_level.txt
awesome_lists_generator-0.2.2.dist-info/RECORD
