Metadata-Version: 2.4
Name: awesome-lists-generator
Version: 0.2.2
Summary: Create markdown based Awesome Lists from yaml files.
Author-email: Derek Vincent <derek@kemiakl.io>
License-Expression: MIT
Keywords: awesome-list,generator
Requires-Python: >=3.12
License-File: LICENSE
Requires-Dist: click>=8.2.0
Requires-Dist: pyyaml>=6.0
Requires-Dist: beautifulsoup4>=4.12.2
Requires-Dist: requests
Provides-Extra: test
Requires-Dist: pytest; extra == "test"
Dynamic: license-file
